cosmux/__init__.py
cosmux/__main__.py
cosmux/_version.py
cosmux/cli.py
cosmux/config.py
cosmux/icon.png
cosmux/logo.png
cosmux/agent/__init__.py
cosmux/agent/compaction.py
cosmux/agent/context.py
cosmux/agent/core.py
cosmux/auth/__init__.py
cosmux/auth/credentials.py
cosmux/auth/oauth.py
cosmux/db/__init__.py
cosmux/db/engine.py
cosmux/db/models.py
cosmux/db/repository.py
cosmux/dev/__init__.py
cosmux/dev/runner.py
cosmux/dev/vite_config.py
cosmux/server/__init__.py
cosmux/server/app.py
cosmux/server/static.py
cosmux/server/routes/__init__.py
cosmux/server/routes/auth.py
cosmux/server/routes/chat.py
cosmux/server/routes/health.py
cosmux/server/routes/sessions.py
cosmux/server/routes/websocket.py
cosmux/static/.gitkeep
cosmux/static/cosmux-standalone.css
cosmux/static/cosmux-standalone.js
cosmux/static/cosmux-standalone.png
cosmux/static/cosmux-standalone2.png
cosmux/static/cosmux-standalone3.png
cosmux/static/cosmux-widget.iife.js
cosmux/static/index-CNIWrd-W.css
cosmux/static/index-CdfRvAfl.js
cosmux/static/index.html
cosmux/static/inject.js
cosmux/static/standalone.html
cosmux/static/assets/icon-BaxqIiZm.png
cosmux/static/assets/index-ClWhg-qd.css
cosmux/static/assets/index-uWYwc1Lc.js
cosmux/static/assets/logo-6JhCMEVJ.png
cosmux/tools/__init__.py
cosmux/tools/ask_user.py
cosmux/tools/base.py
cosmux/tools/bash.py
cosmux/tools/filesystem.py
cosmux-0.4.3.dist-info/METADATA
cosmux-0.4.3.dist-info/WHEEL
cosmux-0.4.3.dist-info/entry_points.txt
cosmux-0.4.3.dist-info/RECORD
