Metadata-Version: 2.4
Name: cosmux
Version: 0.4.3
Summary: AI Coding Agent Widget for Web Development - Code mutates like cosmic radiation
Project-URL: Homepage, https://github.com/techdivision-rnd/cosmux
Project-URL: Documentation, https://github.com/techdivision-rnd/cosmux#readme
Project-URL: Repository, https://github.com/techdivision-rnd/cosmux
Author: Cosmux Team
License-Expression: MIT
Keywords: agent,ai,claude,coding,development,widget
Classifier: Development Status :: 3 - Alpha
Classifier: Environment :: Console
Classifier: Environment :: Web Environment
Classifier: Framework :: FastAPI
Classifier: Intended Audience :: Developers
Classifier: License :: OSI Approved :: MIT License
Classifier: Programming Language :: Python :: 3
Classifier: Programming Language :: Python :: 3.11
Classifier: Programming Language :: Python :: 3.12
Classifier: Topic :: Software Development
Classifier: Topic :: Software Development :: Code Generators
Requires-Python: >=3.11
Requires-Dist: aiosqlite>=0.20.0
Requires-Dist: anthropic>=0.40.0
Requires-Dist: fastapi>=0.115.0
Requires-Dist: pydantic-settings>=2.5.0
Requires-Dist: python-dotenv>=1.0.0
Requires-Dist: rich>=13.0.0
Requires-Dist: sqlmodel>=0.0.22
Requires-Dist: sse-starlette>=2.1.0
Requires-Dist: typer>=0.12.0
Requires-Dist: uvicorn[standard]>=0.30.0
Provides-Extra: dev
Requires-Dist: httpx>=0.27.0; extra == 'dev'
Requires-Dist: mypy>=1.11.0; extra == 'dev'
Requires-Dist: pytest-asyncio>=0.24.0; extra == 'dev'
Requires-Dist: pytest>=8.0.0; extra == 'dev'
Requires-Dist: ruff>=0.6.0; extra == 'dev'
